[
    {
        "datetime": "2025-09-30T02:32:00Z",
        "guild": "Heart and Solo",
        "buff": "Onyxia",
        "notes": "",
        "server": "Doomhowl"
    },
    {
        "datetime": "2025-09-30T03:00:00Z",
        "guild": "Heart and Solo",
        "buff": "Zandalar",
        "notes": "Ninja droppers permitting",
        "server": "Doomhowl"
    },
    {
        "datetime": "2025-09-30T03:02:00Z",
        "guild": "Heart and Solo",
        "buff": "Onyxia",
        "notes": "Ninja droppers permitting",
        "server": "Doomhowl"
    },
    {
        "datetime": "2025-09-30T03:30:00Z",
        "guild": "",
        "buff": "",
        "notes": "Edited time above for today's drop to 9:30pm ST as we had a change in raid plans",
        "server": "Doomhowl"
    },
    {
        "datetime": "2025-09-30T03:32:00Z",
        "guild": "Heart and Solo",
        "buff": "Onyxia",
        "notes": "",
        "server": "Doomhowl"
    },
    {
        "datetime": "2025-09-30T14:25:00Z",
        "guild": "Endless",
        "buff": "Rend",
        "notes": "",
        "server": "Doomhowl"
    },
    {
        "datetime": "2025-09-30T23:50:00Z",
        "guild": "Zug Life",
        "buff": "Zandalar",
        "notes": "",
        "server": "Doomhowl"
    },
    {
        "datetime": "2025-09-30T23:52:00Z",
        "guild": "Zug Life",
        "buff": "Onyxia",
        "notes": "",
        "server": "Doomhowl"
    },
    {
        "datetime": "2025-09-30T23:53:00Z",
        "guild": "Zug Life",
        "buff": "Rend",
        "notes": "layers permitting",
        "server": "Doomhowl"
    },
    {
        "datetime": "2025-10-01T03:00:00Z",
        "guild": "",
        "buff": "",
        "notes": "Raid finished early so we are now dropping at 9pm ST",
        "server": "Doomhowl"
    },
    {
        "datetime": "2025-10-02T02:15:00Z",
        "guild": "fatal",
        "buff": "Zandalar",
        "notes": "",
        "server": "Doomhowl"
    },
    {
        "datetime": "2025-10-02T02:15:00Z",
        "guild": "fatal",
        "buff": "Onyxia",
        "notes": "",
        "server": "Doomhowl"
    },
    {
        "datetime": "2025-10-02T03:30:00Z",
        "guild": "Heart and Solo",
        "buff": "Zandalar",
        "notes": "Ninja droppers permitting",
        "server": "Doomhowl"
    },
    {
        "datetime": "2025-10-02T03:32:00Z",
        "guild": "Heart and Solo",
        "buff": "Nefarian",
        "notes": "Ninja droppers permitting",
        "server": "Doomhowl"
    },
    {
        "datetime": "2025-10-03T00:50:00Z",
        "guild": "Zug Life",
        "buff": "Zandalar",
        "notes": "",
        "server": "Doomhowl"
    },
    {
        "datetime": "2025-10-03T00:52:00Z",
        "guild": "Zug Life",
        "buff": "Nefarian",
        "notes": "",
        "server": "Doomhowl"
    },
    {
        "datetime": "2025-10-03T00:53:00Z",
        "guild": "Zug Life",
        "buff": "Rend",
        "notes": "layers permitting",
        "server": "Doomhowl"
    },
    {
        "datetime": "2025-10-09T07:57:00Z",
        "guild": "Anzacs HC",
        "buff": "Zandalar",
        "notes": "",
        "server": "Doomhowl"
    },
    {
        "datetime": "2025-10-09T08:00:00Z",
        "guild": "Anzacs HC",
        "buff": "Onyxia",
        "notes": "",
        "server": "Doomhowl"
    },
    {
        "datetime": "2025-10-09T08:00:00Z",
        "guild": "Anzacs HC",
        "buff": "Rend",
        "notes": "",
        "server": "Doomhowl"
    }
]